EmaCalc/__init__.py
EmaCalc/dirichlet.py
EmaCalc/ema_base.py
EmaCalc/ema_data.py
EmaCalc/ema_display.py
EmaCalc/ema_display_format.py
EmaCalc/ema_file.py
EmaCalc/ema_group.py
EmaCalc/ema_latent.py
EmaCalc/ema_logging.py
EmaCalc/ema_model.py
EmaCalc/ema_nap.py
EmaCalc/ema_repr.py
EmaCalc/ema_respondent.py
EmaCalc/ema_simulation.py
EmaCalc/ema_thresholds.py
EmaCalc/gauss_gamma.py
EmaCalc/run_ema.py
EmaCalc/run_sim.py
emacalc-1.1.5.dist-info/METADATA
emacalc-1.1.5.dist-info/WHEEL
emacalc-1.1.5.dist-info/licenses/LICENSE.txt
emacalc-1.1.5.dist-info/RECORD
