Metadata-Version: 2.4
Name: EmaCalc
Version: 1.1.5
Summary: Statistical Analysis of Ecological Momentary Assessment (EMA) Data
Author-email: Arne Leijon <leijon@kth.se>
License-Expression: MIT
License-File: LICENSE.txt
Keywords: Bayesian,Momentary Assessment,Nominal Categories,Ordinal Ratings
Classifier: Development Status :: 5 - Production/Stable
Classifier: Intended Audience :: Science/Research
Classifier: Operating System :: OS Independent
Classifier: Programming Language :: Python :: 3
Classifier: Programming Language :: Python :: 3.12
Classifier: Programming Language :: Python :: 3.13
Classifier: Topic :: Multimedia :: Sound/Audio
Classifier: Topic :: Scientific/Engineering :: Information Analysis
Requires-Python: >=3.12
Requires-Dist: matplotlib>=3.9
Requires-Dist: numpy>=2.2
Requires-Dist: openpyxl>=3.1
Requires-Dist: pandas>=2.2
Requires-Dist: samppy>=1.3.1
Requires-Dist: scipy>=1.14
